starpolymers/__init__.py
starpolymers/analysis/__init__.py
starpolymers/analysis/gyr.py
starpolymers/analysis/nc.py
starpolymers/analysis/pmf.py
starpolymers/analysis/rdf.py
starpolymers/analysis/surface.py
starpolymers/analysis/symmetry.py
starpolymers/generators/__init__.py
starpolymers/generators/_configuration.py
starpolymers/generators/colvars.py
starpolymers/generators/configuration.py
starpolymers/generators/input_file.py
starpolymers/generators/system.py
starpolymers/generators/input_files/_00_test.in
starpolymers/generators/input_files/_01_master.in
starpolymers/molecules/__init__.py
starpolymers/molecules/_common.py
starpolymers/molecules/base.py
starpolymers/molecules/brush.py
starpolymers/molecules/polyelectrolyte.py
starpolymers/molecules/salt.py
starpolymers/readers/__init__.py
starpolymers/readers/dumper.py
starpolymers/readers/logger.py
starpolymers/tools/__init__.py
starpolymers/tools/bjerrum.py
starpolymers/tools/cylinders.py
starpolymers/tools/debye.py
starpolymers/tools/design.py
starpolymers/tools/geometry.py
starpolymers/tools/logger.py
starpolymers/tools/neutraliser.py
starpolymers/tools/plotter.py
test/__init__.py
test/test_analysis.py
test/test_generators.py
test/test_molecules.py
test/test_readers.py
test/test_tools.py
starpolymers-2.1.0.dist-info/LICENSE
starpolymers-2.1.0.dist-info/METADATA
starpolymers-2.1.0.dist-info/WHEEL
starpolymers-2.1.0.dist-info/top_level.txt
starpolymers-2.1.0.dist-info/RECORD
