Metadata-Version: 2.1
Name: starpolymers
Version: 2.1.0
Summary: Package for creating polymers for simulation
Home-page: https://github.com/debeshmandal/starpolymers
Author: Debesh Mandal
License: UNKNOWN
Platform: UNKNOWN
Classifier: Programming Language :: Python :: 3
Classifier: License :: OSI Approved :: MIT License
Classifier: Operating System :: OS Independent
Requires-Python: >=3.5
